pmc_ctxdecoextended-0.2-py3.8-nspkg.pth
pmc/ctxdecoextended/__init__.py
pmc/ctxdecoextended/core.py
pmc_ctxdecoextended-0.2.dist-info/METADATA
pmc_ctxdecoextended-0.2.dist-info/WHEEL
pmc_ctxdecoextended-0.2.dist-info/namespace_packages.txt
pmc_ctxdecoextended-0.2.dist-info/top_level.txt
pmc_ctxdecoextended-0.2.dist-info/RECORD
