Metadata-Version: 2.1
Name: pmc-ctxdecoextended
Version: 0.2
Summary: A PMC python module, that extends contextlib.ContextDecorator class to allow the use of decorator without using it as a callable (aka as function)
Home-page: https://github.com/kolotev/python-pmc-singleton
Maintainer: Andrei Kolotev
Maintainer-email: kolotev@ncbi.nlm.nih.gov
License: Public Domain
Platform: UNKNOWN
Classifier: Development Status :: 4 - Beta
Classifier: Topic :: Software Development :: Libraries :: Python Modules
